ligo_cgmi/__init__.py
ligo_cgmi/chirp_probabilities.py
ligo_cgmi/conf.ini
ligo_cgmi/fetch_data_products.py
ligo_cgmi/tests/__init__.py
ligo_cgmi/tests/data/sample_bayestar_map.fits
ligo_cgmi/tests/test_cgmi.py
ligo_cgmi-1.0.5.dist-info/LICENSE
ligo_cgmi-1.0.5.dist-info/METADATA
ligo_cgmi-1.0.5.dist-info/WHEEL
ligo_cgmi-1.0.5.dist-info/entry_points.txt
ligo_cgmi-1.0.5.dist-info/RECORD
