Metadata-Version: 2.3
Name: ligo-cgmi
Version: 1.0.5
Summary: Coarse-grained chirp mass estimates for gravitational-wave events
License: MIT
Author: Andrew Toivonen
Author-email: andrew.toivonen@ligo.org
Requires-Python: >=3.11
Classifier: License :: OSI Approved :: MIT License
Classifier: Programming Language :: Python :: 3
Classifier: Programming Language :: Python :: 3.11
Classifier: Programming Language :: Python :: 3.12
Classifier: Programming Language :: Python :: 3.13
Requires-Dist: astropy
Requires-Dist: h5py
Requires-Dist: ligo-gracedb
Requires-Dist: ligo-skymap (>=2.0.1)
Requires-Dist: matplotlib
Requires-Dist: numpy
Requires-Dist: pandas
